pettingzoo/__init__.py
pettingzoo/atari/__init__.py
pettingzoo/atari/all_modules.py
pettingzoo/atari/base_atari_env.py
pettingzoo/atari/basketball_pong_v3.py
pettingzoo/atari/boxing_v2.py
pettingzoo/atari/combat_plane_v2.py
pettingzoo/atari/combat_tank_v2.py
pettingzoo/atari/double_dunk_v3.py
pettingzoo/atari/entombed_competitive_v3.py
pettingzoo/atari/entombed_cooperative_v3.py
pettingzoo/atari/flag_capture_v2.py
pettingzoo/atari/foozpong_v3.py
pettingzoo/atari/ice_hockey_v2.py
pettingzoo/atari/joust_v3.py
pettingzoo/atari/mario_bros_v3.py
pettingzoo/atari/maze_craze_v3.py
pettingzoo/atari/othello_v3.py
pettingzoo/atari/pong_v3.py
pettingzoo/atari/quadrapong_v4.py
pettingzoo/atari/space_invaders_v2.py
pettingzoo/atari/space_war_v2.py
pettingzoo/atari/surround_v2.py
pettingzoo/atari/tennis_v3.py
pettingzoo/atari/video_checkers_v4.py
pettingzoo/atari/volleyball_pong_v3.py
pettingzoo/atari/warlords_v3.py
pettingzoo/atari/wizard_of_wor_v3.py
pettingzoo/atari/basketball_pong/basketball_pong.py
pettingzoo/atari/boxing/boxing.py
pettingzoo/atari/combat_plane/combat_plane.py
pettingzoo/atari/combat_tank/combat_tank.py
pettingzoo/atari/double_dunk/double_dunk.py
pettingzoo/atari/entombed_competitive/entombed_competitive.py
pettingzoo/atari/entombed_cooperative/entombed_cooperative.py
pettingzoo/atari/flag_capture/flag_capture.py
pettingzoo/atari/foozpong/foozpong.py
pettingzoo/atari/ice_hockey/ice_hockey.py
pettingzoo/atari/joust/joust.py
pettingzoo/atari/mario_bros/mario_bros.py
pettingzoo/atari/maze_craze/maze_craze.py
pettingzoo/atari/othello/othello.py
pettingzoo/atari/pong/pong.py
pettingzoo/atari/quadrapong/quadrapong.py
pettingzoo/atari/space_invaders/space_invaders.py
pettingzoo/atari/space_war/space_war.py
pettingzoo/atari/surround/surround.py
pettingzoo/atari/tennis/tennis.py
pettingzoo/atari/video_checkers/video_checkers.py
pettingzoo/atari/volleyball_pong/volleyball_pong.py
pettingzoo/atari/warlords/warlords.py
pettingzoo/atari/wizard_of_wor/wizard_of_wor.py
pettingzoo-1.24.4.dist-info/licenses/LICENSE
pettingzoo-1.24.4.dist-info/METADATA
pettingzoo-1.24.4.dist-info/WHEEL
pettingzoo-1.24.4.dist-info/top_level.txt
pettingzoo-1.24.4.dist-info/RECORD
