Metadata-Version: 2.4
Name: pettingzoo
Version: 1.24.4
Summary: Gymnasium for multi-agent reinforcement learning.
Author-email: Farama Foundation <contact@farama.org>
License: MIT License
Project-URL: Homepage, https://farama.org
Project-URL: Repository, https://github.com/Farama-Foundation/PettingZoo
Project-URL: Documentation, https://pettingzoo.farama.org
Project-URL: Bug Report, https://github.com/Farama-Foundation/PettingZoo/issues
Keywords: Reinforcement Learning,game,RL,AI,gymnasium
Classifier: Development Status :: 4 - Beta
Classifier: License :: OSI Approved :: MIT License
Classifier: Programming Language :: Python :: 3
Classifier: Programming Language :: Python :: 3.9
Classifier: Programming Language :: Python :: 3.10
Classifier: Programming Language :: Python :: 3.11
Classifier: Programming Language :: Python :: 3.12
Classifier: Intended Audience :: Science/Research
Classifier: Topic :: Scientific/Engineering :: Artificial Intelligence
Requires-Python: <3.13,>=3.9
License-File: LICENSE
Requires-Dist: numpy>=1.21.0
Requires-Dist: gymnasium>=1.0.0
Provides-Extra: atari
Requires-Dist: multi_agent_ale_py>=0.1.11; extra == "atari"
Requires-Dist: pygame>=2.3.0; extra == "atari"
Provides-Extra: classic
Requires-Dist: chess>=1.9.4; extra == "classic"
Requires-Dist: rlcard>=1.0.5; extra == "classic"
Requires-Dist: pygame>=2.3.0; extra == "classic"
Requires-Dist: shimmy[openspiel]>=1.2.0; extra == "classic"
Provides-Extra: butterfly
Requires-Dist: pygame>=2.3.0; extra == "butterfly"
Requires-Dist: pymunk>=6.2.0; extra == "butterfly"
Provides-Extra: mpe
Requires-Dist: pygame>=2.3.0; extra == "mpe"
Provides-Extra: sisl
Requires-Dist: pygame>=2.3.0; extra == "sisl"
Requires-Dist: pymunk>=6.2.0; extra == "sisl"
Requires-Dist: box2d-py>=2.3.5; extra == "sisl"
Requires-Dist: scipy>=1.4.1; extra == "sisl"
Provides-Extra: other
Requires-Dist: pillow>=8.0.1; extra == "other"
Provides-Extra: testing
Requires-Dist: pynput>=1.7.6; extra == "testing"
Requires-Dist: pytest>=8.0.0; extra == "testing"
Requires-Dist: AutoROM>=0.6.1; extra == "testing"
Requires-Dist: pytest-cov>=4.1.0; extra == "testing"
Requires-Dist: pytest-xdist>=3.5.0; extra == "testing"
Requires-Dist: pre-commit>=3.5.0; extra == "testing"
Requires-Dist: pytest-markdown-docs>=0.5.0; extra == "testing"
Provides-Extra: all
Requires-Dist: multi_agent_ale_py>=0.1.11; extra == "all"
Requires-Dist: pygame>=2.3.0; extra == "all"
Requires-Dist: chess>=1.9.4; extra == "all"
Requires-Dist: rlcard>=1.0.5; extra == "all"
Requires-Dist: shimmy[openspiel]>=1.2.0; extra == "all"
Requires-Dist: pymunk>=6.2.0; extra == "all"
Requires-Dist: box2d-py>=2.3.5; extra == "all"
Requires-Dist: scipy>=1.4.1; extra == "all"
Requires-Dist: pillow>=8.0.1; extra == "all"
Dynamic: license-file
